wowapi/__init__.py
wowapi/api.py
wowapi/exceptions.py
wowapi/mixins/__init__.py
wowapi/mixins/game_data.py
wowapi/mixins/profile.py
python_wowapi-4.0.0.dist-info/LICENSE.txt
python_wowapi-4.0.0.dist-info/METADATA
python_wowapi-4.0.0.dist-info/WHEEL
python_wowapi-4.0.0.dist-info/top_level.txt
python_wowapi-4.0.0.dist-info/RECORD
