Metadata-Version: 2.1
Name: python-wowapi
Version: 4.0.0
Summary: Python-wowapi is a client library for the World of Warcraft, Data and Profile API's.
Home-page: https://github.com/lockwooddev/python-wowapi
Author: Carlo Smouter
Author-email: lockwooddev@gmail.com
License: MIT
Keywords: warcraft,api,wow,auctionhouse,community,game,data,profile,blizzard,classic,wow
Platform: UNKNOWN
Classifier: Development Status :: 5 - Production/Stable
Classifier: Intended Audience :: Developers
Classifier: License :: OSI Approved :: MIT License
Classifier: Operating System :: OS Independent
Classifier: Programming Language :: Python
Classifier: Programming Language :: Python :: 3.5
Classifier: Programming Language :: Python :: 3.6
Classifier: Programming Language :: Python :: 3.7
Classifier: Topic :: Internet :: WWW/HTTP
Requires-Dist: requests (==2.23.0)
Provides-Extra: docs
Requires-Dist: pydoc-markdown (==2.0.5) ; extra == 'docs'
Provides-Extra: tests
Requires-Dist: pytest (<6.0,>=5.0) ; extra == 'tests'
Requires-Dist: pytest-flake8 ; extra == 'tests'
Requires-Dist: pytest-isort (==1.0.0) ; extra == 'tests'
Requires-Dist: pytest-cov (<3.0,>=2.7) ; extra == 'tests'
Requires-Dist: pytest-mock (==1.10.4) ; extra == 'tests'
